{
    "packages": [],
    "includes": {
        "include/all$bec7a5c500d820425a7ffab501af61e4a0aae054.json": {
            "sha1": "bec7a5c500d820425a7ffab501af61e4a0aae054"
        }
    },
    "metadata-url": "/p2/%package%.json",
    "available-packages": [
        "cfc/cfc-theme",
        "cfc/chorus-php-client",
        "cfc/codex-client",
        "cfc/directory-client",
        "cfc/electre-client",
        "cfc/erp-client",
        "cfc/hermes-client",
        "cfc/site-php-client",
        "cfc/yellowbox-client",
        "mono/maker-bundle"
    ]
}
